[{"name":"vc.builder.install","duration":15644983,"timestamp":3002998535,"id":"2e109ee9-b2de-41d5-93df-5c5a9b1a23dd","parentId":"8a43117b-b13b-4081-82d7-a78c5118ac16","tags":{"cliType":"npm","lockfileVersion":"3"},"startTime":1774402686190},{"name":"vc.builder.build","duration":59677985,"timestamp":3018647712,"id":"b71bfece-7f3f-4933-9193-868b98278c76","parentId":"8a43117b-b13b-4081-82d7-a78c5118ac16","tags":{"buildScriptName":"build"},"startTime":1774402701839},{"name":"vc.builder","duration":78275514,"timestamp":3002965896,"id":"8a43117b-b13b-4081-82d7-a78c5118ac16","parentId":"0691c971-9a69-4094-8113-2296b418b1ea","tags":{"builder.name":"@vercel/next","builder.version":"4.16.2","builder.dynamicallyInstalled":"false","install":"true","build":"true"},"startTime":1774402686157},{"name":"vc.builder.diagnostics","duration":3032,"timestamp":3081241613,"id":"2027c5b5-c311-4258-ad10-0912f1f33b0b","parentId":"8a43117b-b13b-4081-82d7-a78c5118ac16","tags":{},"startTime":1774402764433},{"name":"vc.doBuild","duration":82063524,"timestamp":2999188091,"id":"0691c971-9a69-4094-8113-2296b418b1ea","parentId":"b640df0f-4393-4789-a5a4-ccbe2b9b001a","tags":{},"startTime":1774402682379},{"name":"vc","duration":82085261,"timestamp":2999166395,"id":"b640df0f-4393-4789-a5a4-ccbe2b9b001a","tags":{},"startTime":1774402682357}]